{
    "Million": {
        "max": "4.7", 
        "mean": 4.7, 
        "min": "4.7"
    }, 
    "km": {
        "max": "995", 
        "mean": 993.5490374492749, 
        "min": "0.1"
    }, 
    "meter": {
        "max": "500", 
        "mean": 248.77460317460316, 
        "min": "5.4"
    }, 
    "years": {
        "max": "7", 
        "mean": 14.786024878778502, 
        "min": "000"
    }, 
    "mile": {
        "max": "4", 
        "mean": 4.0, 
        "min": "4"
    }, 
    "tH": {
        "max": "100", 
        "mean": 100.0, 
        "min": "100"
    }, 
    "Miles": {
        "max": "6015", 
        "mean": 1615.4158512720157, 
        "min": "10025"
    }, 
    "LI": {
        "max": "2", 
        "mean": 2.0, 
        "min": "2"
    }, 
    "SIO": {
        "max": "1", 
        "mean": 1.0, 
        "min": "1"
    }, 
    "PRE": {
        "max": "3.1", 
        "mean": 3.1, 
        "min": "3.1"
    }, 
    "RS": {
        "max": "2009", 
        "mean": 2009.0, 
        "min": "2009"
    }, 
    "GHz": {
        "max": "89.0", 
        "mean": 26.622491798275732, 
        "min": "10"
    }, 
    "acres": {
        "max": "10", 
        "mean": 1.5, 
        "min": "0.25"
    }, 
    "to": {
        "max": "9000", 
        "mean": 1499.8801060243375, 
        "min": "0"
    }, 
    "degrees": {
        "max": "98.8", 
        "mean": 37.297096628138696, 
        "min": "0"
    }, 
    "th": {
        "max": "9", 
        "mean": 11.026429324625283, 
        "min": "10"
    }, 
    "On": {
        "max": "7.3", 
        "mean": 7.3, 
        "min": "7.3"
    }, 
    "psi": {
        "max": "100", 
        "mean": 100.0, 
        "min": "100"
    }, 
    "D": {
        "max": "88", 
        "mean": 11.226022616980746, 
        "min": "03"
    }, 
    "EG": {
        "max": "3", 
        "mean": 3.0, 
        "min": "3"
    }, 
    "H": {
        "max": "9", 
        "mean": 5.9035367850346, 
        "min": "00"
    }, 
    "de": {
        "max": "6", 
        "mean": 53.98412698412698, 
        "min": "1"
    }, 
    "L": {
        "max": "480", 
        "mean": 171.63529411764705, 
        "min": "07"
    }, 
    "P": {
        "max": "95", 
        "mean": 84.15054731473411, 
        "min": "00"
    }, 
    "T": {
        "max": "874", 
        "mean": 2235.9133958217717, 
        "min": "0.58"
    }, 
    "hPa": {
        "max": "850", 
        "mean": 121.01910785382013, 
        "min": "0.001"
    }, 
    "Minutes": {
        "max": "30", 
        "mean": 15.70973747053124, 
        "min": "08"
    }, 
    "day": {
        "max": "7", 
        "mean": 2.445400720258805, 
        "min": "1"
    }, 
    "minute": {
        "max": "6", 
        "mean": 3.3333333333333335, 
        "min": "1"
    }, 
    "Pre": {
        "max": "5.3", 
        "mean": 1040.6935483870966, 
        "min": "2.7"
    }, 
    "Ars": {
        "max": "24", 
        "mean": 24.0, 
        "min": "24"
    }, 
    "d": {
        "max": "90", 
        "mean": 87.81590497360173, 
        "min": "1"
    }, 
    "pounds": {
        "max": "930", 
        "mean": 828.5826771653543, 
        "min": "000"
    }, 
    "h": {
        "max": "0004", 
        "mean": 1.6313725490196078, 
        "min": "0.00"
    }, 
    "f": {
        "max": "5", 
        "mean": 131.20000000000002, 
        "min": "2001"
    }, 
    "dB": {
        "max": "10", 
        "mean": 1.8571428571428572, 
        "min": "0.5"
    }, 
    "l": {
        "max": "3", 
        "mean": 4.032258064516129, 
        "min": "11"
    }, 
    "p": {
        "max": "85", 
        "mean": 4.2842047635179625, 
        "min": "0"
    }, 
    "miles": {
        "max": "438", 
        "mean": 172.65681845928458, 
        "min": "000"
    }, 
    "gram": {
        "max": "9", 
        "mean": 9.0, 
        "min": "9"
    }, 
    "nanome": {
        "max": "532", 
        "mean": 532.0, 
        "min": "532"
    }, 
    "square": {
        "max": "15", 
        "mean": 15.0, 
        "min": "15"
    }, 
    "bytes": {
        "max": "210", 
        "mean": 210.0, 
        "min": "210"
    }, 
    "ea": {
        "max": "227", 
        "mean": 227.0, 
        "min": "227"
    }, 
    "Mg": {
        "max": "62", 
        "mean": 62.0, 
        "min": "62"
    }, 
    "Ren": {
        "max": "2012", 
        "mean": 2012.0, 
        "min": "2012"
    }, 
    "HO": {
        "max": "2", 
        "mean": 2.0, 
        "min": "2"
    }, 
    "year": {
        "max": "50", 
        "mean": 286.7847358121331, 
        "min": "1"
    }, 
    "ft": {
        "max": "500", 
        "mean": 266.1995982079206, 
        "min": "000"
    }, 
    "Ph": {
        "max": "80237", 
        "mean": 386.4134831460675, 
        "min": "1999"
    }, 
    "es": {
        "max": "9", 
        "mean": 9.0, 
        "min": "9"
    }, 
    "PS": {
        "max": "3", 
        "mean": 3.0, 
        "min": "3"
    }, 
    "degree": {
        "max": "4", 
        "mean": 2.3581635767147326, 
        "min": "0.125"
    }, 
    "Hours": {
        "max": "208", 
        "mean": 76.0, 
        "min": "10"
    }, 
    "kilometer": {
        "max": "1", 
        "mean": 1.0, 
        "min": "1"
    }, 
    "am": {
        "max": "45", 
        "mean": 8.311876769079355, 
        "min": "00"
    }, 
    "PO": {
        "max": "3", 
        "mean": 1.0, 
        "min": "00"
    }, 
    "PM": {
        "max": "57", 
        "mean": 11.913595342031705, 
        "min": "00"
    }, 
    "EL": {
        "max": "2015", 
        "mean": 2015.0, 
        "min": "2015"
    }, 
    "C": {
        "max": "9", 
        "mean": 603.818792084978, 
        "min": "0"
    }, 
    "EN": {
        "max": "59", 
        "mean": 59.0, 
        "min": "59"
    }, 
    "million hectares": {
        "max": "936", 
        "mean": 391.2875299386698, 
        "min": "1.05"
    }, 
    "G": {
        "max": "5700", 
        "mean": 376.45980422824266, 
        "min": "0"
    }, 
    "Mb": {
        "max": "985", 
        "mean": 240.55098117007967, 
        "min": "096"
    }, 
    "EE": {
        "max": "1207", 
        "mean": 1207.0, 
        "min": "1207"
    }, 
    "M": {
        "max": "98.3", 
        "mean": 47.73857928299785, 
        "min": "0.01"
    }, 
    "K": {
        "max": "87", 
        "mean": 174.65417970747416, 
        "min": "1"
    }, 
    "million": {
        "max": "9", 
        "mean": 265.2250970282596, 
        "min": "1"
    }, 
    "Mi": {
        "max": "10", 
        "mean": 10.0, 
        "min": "10"
    }, 
    "O": {
        "max": "4", 
        "mean": 4.078128679655492, 
        "min": "00"
    }, 
    "hours": {
        "max": "92", 
        "mean": 86.92066813670485, 
        "min": "000"
    }, 
    "S": {
        "max": "6.99", 
        "mean": 32.96359166857405, 
        "min": "02"
    }, 
    "square meters": {
        "max": "047", 
        "mean": 47.0, 
        "min": "047"
    }, 
    "W": {
        "max": "800", 
        "mean": 168.67553119536075, 
        "min": "04"
    }, 
    "kilometers": {
        "max": "50", 
        "mean": 13.202463529268146, 
        "min": "0.01"
    }, 
    "r": {
        "max": "5383", 
        "mean": 3851.5714285714284, 
        "min": "023"
    }, 
    "by": {
        "max": "1983", 
        "mean": 1475.1290322580646, 
        "min": "15.00"
    }, 
    "million km": {
        "max": "5.0", 
        "mean": 5.4, 
        "min": "0.4"
    }, 
    "on": {
        "max": "9", 
        "mean": 4.726584673604541, 
        "min": "1"
    }, 
    "c": {
        "max": "720", 
        "mean": 373.27481979138264, 
        "min": "0"
    }, 
    "square feet": {
        "max": "560", 
        "mean": 373.3333333333333, 
        "min": "000"
    }, 
    "g": {
        "max": "46.07", 
        "mean": 8.140352250489235, 
        "min": "0.039"
    }, 
    "MB": {
        "max": "84", 
        "mean": 13.238433714788039, 
        "min": "000"
    }, 
    "gallons": {
        "max": "500", 
        "mean": 500.0, 
        "min": "500"
    }, 
    "k": {
        "max": "5", 
        "mean": 128.66929133858267, 
        "min": "0111"
    }, 
    "months": {
        "max": "9", 
        "mean": 8.176067826271563, 
        "min": "12"
    }, 
    "calories": {
        "max": "2.3881011", 
        "mean": 2.3881011, 
        "min": "2.3881011"
    }, 
    "days": {
        "max": "90", 
        "mean": 26.181532865301428, 
        "min": "10"
    }, 
    "o": {
        "max": "1", 
        "mean": 1.0, 
        "min": "1"
    }, 
    "Years": {
        "max": "4", 
        "mean": 14.714285714285714, 
        "min": "23"
    }, 
    "s": {
        "max": "70", 
        "mean": 1957.8249411054455, 
        "min": "1"
    }, 
    "UN": {
        "max": "2010", 
        "mean": 2010.0, 
        "min": "2010"
    }, 
    "Meters": {
        "max": "519", 
        "mean": 519.0, 
        "min": "519"
    }, 
    "w": {
        "max": "56", 
        "mean": 1323.3333333333333, 
        "min": "1957"
    }, 
    "Watts": {
        "max": "2", 
        "mean": 2.0, 
        "min": "2"
    }, 
    "deg": {
        "max": "9.8076", 
        "mean": 2.107648199890328, 
        "min": "0.164"
    }, 
    "or": {
        "max": "8124", 
        "mean": 2105.529132737136, 
        "min": "0"
    }, 
    "cm": {
        "max": "86", 
        "mean": 40.42759206519126, 
        "min": "1"
    }, 
    "No": {
        "max": "1973", 
        "mean": 1055.5333333333333, 
        "min": "07"
    }, 
    "IN": {
        "max": "5.2", 
        "mean": 5.2, 
        "min": "5.2"
    }, 
    "feet": {
        "max": "800", 
        "mean": 67.34143498031555, 
        "min": "000"
    }, 
    "cr": {
        "max": "9", 
        "mean": 7.78740157480315, 
        "min": "4"
    }, 
    "HFC": {
        "max": "2", 
        "mean": 2.0, 
        "min": "2"
    }, 
    "NH": {
        "max": "5", 
        "mean": 5.0, 
        "min": "5"
    }, 
    "NI": {
        "max": "33", 
        "mean": 33.0, 
        "min": "33"
    }, 
    "fee": {
        "max": "000", 
        "mean": 0.0, 
        "min": "000"
    }, 
    "Ft": {
        "max": "1", 
        "mean": 1.0, 
        "min": "1"
    }, 
    "log": {
        "max": "5861544.0", 
        "mean": 3286421.3399999994, 
        "min": "2826.9"
    }, 
    "Degree": {
        "max": "4", 
        "mean": 1.7333333333333334, 
        "min": "1"
    }, 
    "area": {
        "max": "1850", 
        "mean": 1850.0, 
        "min": "1850"
    }, 
    "NA": {
        "max": "57", 
        "mean": 57.0, 
        "min": "57"
    }, 
    "NC": {
        "max": "6", 
        "mean": 6.0, 
        "min": "6"
    }, 
    "ND": {
        "max": "5.8", 
        "mean": 5.8, 
        "min": "5.8"
    }, 
    "t": {
        "max": "21", 
        "mean": 13.428571428571429, 
        "min": "0"
    }, 
    "ton": {
        "max": "1", 
        "mean": 1.0, 
        "min": "1"
    }, 
    "Fe": {
        "max": "2", 
        "mean": 2.0, 
        "min": "2"
    }, 
    "HS": {
        "max": "40", 
        "mean": 37.333333333333336, 
        "min": "36"
    }, 
    "wat": {
        "max": "300", 
        "mean": 300.0, 
        "min": "300"
    }, 
    "pm": {
        "max": "7", 
        "mean": 2.9875500704107303, 
        "min": "00"
    }, 
    "B": {
        "max": "44", 
        "mean": 13.18787271558993, 
        "min": "01"
    }, 
    "F": {
        "max": "95578", 
        "mean": 1331.5555211244418, 
        "min": "1"
    }, 
    "hr": {
        "max": "7", 
        "mean": 4.028571428571429, 
        "min": "1.8"
    }, 
    "LON": {
        "max": "5.0", 
        "mean": 5.0, 
        "min": "5.0"
    }, 
    "Ki": {
        "max": "29", 
        "mean": 29.0, 
        "min": "29"
    }, 
    "Kilometers": {
        "max": "5025", 
        "mean": 1164.0054550222922, 
        "min": "10050"
    }, 
    "watts": {
        "max": "66", 
        "mean": 66.0, 
        "min": "66"
    }, 
    "Km": {
        "max": "800", 
        "mean": 450.98983905742864, 
        "min": "0.5"
    }, 
    "N": {
        "max": "8", 
        "mean": 54.97895307020884, 
        "min": "168"
    }, 
    "gal": {
        "max": "100", 
        "mean": 100.0, 
        "min": "100"
    }, 
    "V": {
        "max": "591", 
        "mean": 4.253333333333333, 
        "min": "1"
    }, 
    "Z": {
        "max": "8044", 
        "mean": 1878.7045009784736, 
        "min": "11"
    }, 
    "MINUTES": {
        "max": "3", 
        "mean": 3.0, 
        "min": "3"
    }, 
    "he": {
        "max": "1984", 
        "mean": 1984.0, 
        "min": "1984"
    }, 
    "microns": {
        "max": "30", 
        "mean": 9.428571428571429, 
        "min": "1.2"
    }, 
    "b": {
        "max": "7336859", 
        "mean": 1959.3247111876158, 
        "min": "01"
    }, 
    "cal": {
        "max": "9", 
        "mean": 6.333333333333333, 
        "min": "1"
    }, 
    "hour": {
        "max": "24", 
        "mean": 14.142857142857142, 
        "min": "1"
    }, 
    "mb": {
        "max": "850", 
        "mean": 390.49740564636403, 
        "min": "0"
    }, 
    "mm": {
        "max": "85", 
        "mean": 116.91334456970311, 
        "min": "0.2"
    }, 
    "KH": {
        "max": "7", 
        "mean": 7.0, 
        "min": "7"
    }, 
    "KM": {
        "max": "2", 
        "mean": 2.0, 
        "min": "2"
    }, 
    "n": {
        "max": "6", 
        "mean": 761.9333333333333, 
        "min": "0"
    }, 
    "ua": {
        "max": "7", 
        "mean": 7.0, 
        "min": "7"
    }, 
    "un": {
        "max": "3", 
        "mean": 3.0, 
        "min": "3"
    }, 
    "Ze": {
        "max": "00", 
        "mean": 0.0, 
        "min": "00"
    }, 
    "meters": {
        "max": "5", 
        "mean": 5.4883221896383185, 
        "min": "0.000000"
    }, 
    "minutes": {
        "max": "90", 
        "mean": 27.322688828887195, 
        "min": "100"
    }, 
    "are": {
        "max": "4", 
        "mean": 270.26666666666665, 
        "min": "2007"
    }, 
    "v": {
        "max": "4", 
        "mean": 19.5748031496063, 
        "min": "08"
    }, 
    "vol": {
        "max": "1.2", 
        "mean": 0.9333333333333332, 
        "min": "0.4"
    }, 
    "DB": {
        "max": "45", 
        "mean": 1340.3333333333333, 
        "min": "1988"
    }, 
    "al": {
        "max": "9", 
        "mean": 9.0, 
        "min": "9"
    }, 
    "CH": {
        "max": "3", 
        "mean": 3.0, 
        "min": "3"
    }, 
    "at": {
        "max": "8.90", 
        "mean": 27.781985351338975, 
        "min": "07.09"
    }, 
    "Th": {
        "max": "6", 
        "mean": 14.0, 
        "min": "30"
    }, 
    "in": {
        "max": "9", 
        "mean": 1048.6743825865371, 
        "min": "000"
    }, 
    "Tg": {
        "max": "74.8", 
        "mean": 319.62096989628066, 
        "min": "0.1"
    }, 
    "Month": {
        "max": "96", 
        "mean": 31.558622583856902, 
        "min": "24"
    }, 
    "DS": {
        "max": "95", 
        "mean": 95.0, 
        "min": "95"
    }, 
    "ni": {
        "max": "1", 
        "mean": 1.0, 
        "min": "1"
    }, 
    "nm": {
        "max": "865", 
        "mean": 234.71272141803502, 
        "min": "0.148"
    }, 
    "min": {
        "max": "5", 
        "mean": 12.803691510882164, 
        "min": "1"
    }, 
    "TT": {
        "max": "2", 
        "mean": 2.0, 
        "min": "2"
    }, 
    "nc": {
        "max": "2", 
        "mean": 2.0, 
        "min": "2"
    }, 
    "nd": {
        "max": "32", 
        "mean": 7.123443901687961, 
        "min": "2"
    }, 
    "Ci": {
        "max": "5", 
        "mean": 5.0, 
        "min": "5"
    }, 
    "Da": {
        "max": "46", 
        "mean": 46.0, 
        "min": "46"
    }, 
    "kilograms": {
        "max": "325", 
        "mean": 325.0, 
        "min": "325"
    }, 
    "LT": {
        "max": "7", 
        "mean": 7.0, 
        "min": "7"
    }, 
    "TH": {
        "max": "5", 
        "mean": 5.0, 
        "min": "5"
    }, 
    "inch": {
        "max": "5", 
        "mean": 5.0, 
        "min": "5"
    }, 
    "MHz": {
        "max": "10", 
        "mean": 10.0, 
        "min": "10"
    }, 
    "A": {
        "max": "94", 
        "mean": 25.378640197233736, 
        "min": "00"
    }, 
    "mintues": {
        "max": "100", 
        "mean": 100.0, 
        "min": "100"
    }, 
    "E": {
        "max": "9", 
        "mean": 64.70702070240873, 
        "min": "0"
    }, 
    "MS": {
        "max": "61", 
        "mean": 61.0, 
        "min": "61"
    }, 
    "I": {
        "max": "5", 
        "mean": 376.8645161290322, 
        "min": "13"
    }, 
    "AM": {
        "max": "52", 
        "mean": 8.079383428827022, 
        "min": "00"
    }, 
    "Q": {
        "max": "91", 
        "mean": 2391.6545536388676, 
        "min": "00"
    }, 
    "hectares": {
        "max": "700", 
        "mean": 200.23125714285717, 
        "min": "0.4047"
    }, 
    "beta": {
        "max": "13", 
        "mean": 13.0, 
        "min": "13"
    }, 
    "AR": {
        "max": "4", 
        "mean": 28.666666666666668, 
        "min": "130"
    }, 
    "U": {
        "max": "9", 
        "mean": 4443.569658187922, 
        "min": "112"
    }, 
    "kil": {
        "max": "50", 
        "mean": 50.0, 
        "min": "50"
    }, 
    "Y": {
        "max": "9115", 
        "mean": 6722.333333333333, 
        "min": "1937"
    }, 
    "mil": {
        "max": "2", 
        "mean": 2.0, 
        "min": "2"
    }, 
    "a": {
        "max": "947", 
        "mean": 365.63030756045623, 
        "min": "00"
    }, 
    "US": {
        "max": "888", 
        "mean": 597.6666666666666, 
        "min": "17"
    }, 
    "All": {
        "max": "14", 
        "mean": 12.666666666666666, 
        "min": "10"
    }, 
    "e": {
        "max": "9.999", 
        "mean": 1.2676505980080308, 
        "min": "02"
    }, 
    "grams": {
        "max": "20", 
        "mean": 20.0, 
        "min": "20"
    }, 
    "i": {
        "max": "2", 
        "mean": 1.6714285714285713, 
        "min": "1"
    }, 
    "sq": {
        "max": "900", 
        "mean": 350.6248188941785, 
        "min": "0.42"
    }, 
    "no": {
        "max": "0", 
        "mean": 0.0, 
        "min": "0"
    }, 
    "m": {
        "max": "927", 
        "mean": 60.61958836058659, 
        "min": "0"
    }, 
    "It": {
        "max": "9", 
        "mean": 9.0, 
        "min": "9"
    }, 
    "kilogram": {
        "max": "1", 
        "mean": 1.0, 
        "min": "1"
    }, 
    "q": {
        "max": "401354", 
        "mean": 401354.0, 
        "min": "401354"
    }, 
    "R": {
        "max": "9", 
        "mean": 78.7275785972187, 
        "min": "00"
    }, 
    "Im": {
        "max": "12", 
        "mean": 12.0, 
        "min": "12"
    }, 
    "At": {
        "max": "3.2", 
        "mean": 3.2, 
        "min": "3.2"
    }, 
    "Ts": {
        "max": "3", 
        "mean": 3.0, 
        "min": "3"
    }, 
    "Year": {
        "max": "6", 
        "mean": 298.57142857142856, 
        "min": "18"
    }, 
    "y": {
        "max": "43", 
        "mean": 12.533333333333333, 
        "min": "1"
    }, 
    "GB": {
        "max": "60.0", 
        "mean": 11.073985717337562, 
        "min": "11.7"
    }
}